pytest_gui_status/utils.py
pytest_gui_status/__init__.py
pytest_gui_status/status_gui/gui_backend.py
pytest_gui_status/status_gui/gui_frontend.py
pytest_gui_status/status_gui/utils_gui.py
pytest_gui_status/status_gui/__init__.py
pytest_gui_status/status_gui/tmpl/index.html
pytest_gui_status/status_gui/tmpl/refresh.js
pytest_gui_status/status_plugin/plugin.py
pytest_gui_status/status_plugin/__init__.py
pytest_gui_status-0.0.4.dist-info/DESCRIPTION.rst
pytest_gui_status-0.0.4.dist-info/entry_points.txt
pytest_gui_status-0.0.4.dist-info/METADATA
pytest_gui_status-0.0.4.dist-info/metadata.json
pytest_gui_status-0.0.4.dist-info/RECORD
pytest_gui_status-0.0.4.dist-info/top_level.txt
pytest_gui_status-0.0.4.dist-info/WHEEL
