Metadata-Version: 2.0
Name: pytest-gui-status
Version: 0.0.4
Summary: Show pytest status in gui
Home-page: UNKNOWN
Author: Abhas Bhattacharya
Author-email: abhasbhattacharya2@gmail.com
License: MIT
Platform: any
Requires-Dist: redis
Requires-Dist: pytest
Requires-Dist: htmlpy
Requires-Dist: jinja2
Requires-Dist: python-dateutil
Requires-Dist: humanfriendly
Requires-Dist: psutil
Requires-Dist: setuptools
Requires-Dist: mock
